adr/__init__.py
adr/cli.py
adr/configuration.py
adr/context.py
adr/errors.py
adr/export/__init__.py
adr/export/gist.py
adr/export/test.py
adr/formatter.py
adr/query.py
adr/recipe.py
adr/sources.py
adr/util/__init__.py
adr/util/cache_stores.py
adr/util/datastructures.py
adr/util/memoize.py
adr/util/req.py
app/__init__.py
app/app.py
app/static/adr.js
app/static/recipe.js
app/templates/home.html
app/templates/layout.html
app/templates/recipe.html
extra/completion.bash
extra/gen_recipe_docs.py
recipes/__init__.py
recipes/context.yml
recipes/inspect.py
recipes/queries/meta.query
recipes/queries/meta_columns.query
recipes/queries/meta_values.query
adr-0.19.4.dist-info/entry_points.txt
adr-0.19.4.dist-info/LICENSE
adr-0.19.4.dist-info/WHEEL
adr-0.19.4.dist-info/METADATA
adr-0.19.4.dist-info/RECORD
