Metadata-Version: 2.1
Name: adr
Version: 0.19.4
Summary: Utility for running ActiveData recipes
Home-page: https://github.com/mozilla/adr
License: MPL-2.0
Author: Andrew Halberstadt
Author-email: ahalberstadt@mozilla.com
Requires-Python: >=3.6,<4
Classifier: License :: OSI Approved
Classifier: Programming Language :: Python :: 3
Classifier: Programming Language :: Python :: 3.6
Classifier: Programming Language :: Python :: 3.7
Classifier: Programming Language :: Python :: 3.8
Provides-Extra: app
Requires-Dist: appdirs (>=1,<2)
Requires-Dist: boto3 (>=1,<2)
Requires-Dist: cachy (>=0,<1)
Requires-Dist: docutils (>=0,<1)
Requires-Dist: flask (>=1,<2); extra == "app"
Requires-Dist: json-e (>=3,<4)
Requires-Dist: loguru (>=0,<1)
Requires-Dist: markdown (>=3,<4)
Requires-Dist: pygments (>=2,<3)
Requires-Dist: python3-memcached (>=1,<2)
Requires-Dist: pyyaml (>=5,<6)
Requires-Dist: redis (>=3,<4)
Requires-Dist: requests (>=2,<3)
Requires-Dist: taskcluster (>=38,<39)
Requires-Dist: terminaltables (>=3,<4)
Requires-Dist: tomlkit (>=0,<1)
Requires-Dist: zstandard (>=0,<1)
Project-URL: Repository, https://github.com/mozilla/adr
